{
    "name": "Welcomes",
    "id": "welcome",
    "description": "Welcome component, just show welcome message instead of hello world.",
    "version": "1.0.0",
    "status": true,
    "author": {
        "name": "Malik Umer Farooq",
        "email": "lablnet01@gmail.com",
        "homepage": "https:\/\/zestframework.xyz"
    },
    "requires": {
        "version": "3.0.0",
        "comparator": ">="
    },
    "license": {
        "license": "MIT",
        "url": "https:\/\/opensource.org\/licenses\/MIT"
    }
}